jdb_to_nwb/resources/Get_Hex_Centroids.ipynb
jdb_to_nwb/resources/README.md
jdb_to_nwb/resources/electrophysiology/252ch_probe_10mm_length_100um_pitch_coords.csv
jdb_to_nwb/resources/electrophysiology/252ch_probe_10mm_length_100um_pitch_coords.png
jdb_to_nwb/resources/electrophysiology/252ch_probe_4mm_length_80um_pitch_coords.csv
jdb_to_nwb/resources/electrophysiology/252ch_probe_4mm_length_80um_pitch_coords.png
jdb_to_nwb/resources/electrophysiology/252ch_silicon_probe_channel_map.csv
jdb_to_nwb/resources/electrophysiology/256ch_probe_3mm_length_66um_pitch_coords.csv
jdb_to_nwb/resources/electrophysiology/256ch_probe_3mm_length_66um_pitch_coords.png
jdb_to_nwb/resources/electrophysiology/256ch_probe_6mm_length_80um_pitch_coords.csv
jdb_to_nwb/resources/electrophysiology/256ch_probe_6mm_length_80um_pitch_coords.png
jdb_to_nwb/resources/electrophysiology/256ch_silicon_probe_channel_map.csv
jdb_to_nwb/resources/electrophysiology/README.md
jdb_to_nwb/resources/electrophysiology/ephys_devices.yaml
jdb_to_nwb/resources/electrophysiology/generate_electrode_coordinates.ipynb
jdb_to_nwb/resources/electrophysiology/neuropixels_2.0_multishank_all_electrodes.png
jdb_to_nwb/resources/electrophysiology/neuropixels_2.0_multishank_electrode_coords.csv
jdb_to_nwb/resources/frank_lab/centroids/20240222_MazeNoBarriers_hex_coordinates.csv
jdb_to_nwb/resources/frank_lab/centroids/20240530_BraveLu_hex_coordinates.csv
jdb_to_nwb/resources/frank_lab/centroids/20240629_Hexmaze_hex_coordinates.csv
jdb_to_nwb/resources/frank_lab/centroids/20241123_Mario_hex_coordinates.csv
jdb_to_nwb/resources/frank_lab/centroids/20250210_Luna_hex_coordinates.csv
jdb_to_nwb/resources/frank_lab/centroids/hex_coordinates.csv
jdb_to_nwb/resources/frank_lab/video_files/20240222_MazeNoBarriers.1.h264
jdb_to_nwb/resources/frank_lab/video_files/20240530_BraveLu_Maze_No_Barrier.1.h264
jdb_to_nwb/resources/frank_lab/video_files/20240629_Hexmaze_permanent_barriers.1.h264
jdb_to_nwb-2.1.1.dist-info/METADATA
jdb_to_nwb-2.1.1.dist-info/WHEEL
jdb_to_nwb-2.1.1.dist-info/entry_points.txt
jdb_to_nwb-2.1.1.dist-info/RECORD
