Metadata-Version: 2.4
Name: jdb_to_nwb
Version: 2.1.1
Summary: Converts electrophysiology, photometry, and behavioral data for the hex maze task used by the Berke Lab at UCSF to NWB format for sharing and analysis.
Project-URL: Homepage, https://github.com/calderast/jdb_to_nwb/
Project-URL: Bug Tracker, https://github.com/calderast/jdb_to_nwb/issues
Author: Stephanie Crater, Ryan Ly, Yang-Sun Hwang, Jose Figueroa
Maintainer-email: Stephanie Crater <stephcrater@berkeley.edu>
License: BSD-3-Clause
Classifier: Development Status :: 5 - Production/Stable
Classifier: Intended Audience :: Science/Research
Classifier: License :: OSI Approved :: BSD License
Classifier: Operating System :: OS Independent
Classifier: Programming Language :: Python
Classifier: Programming Language :: Python :: 3.12
Requires-Python: >=3.12
Requires-Dist: ffmpeg-python
Requires-Dist: hex-maze-neuro
Requires-Dist: imageio-ffmpeg
Requires-Dist: matplotlib
Requires-Dist: ndx-fiber-photometry
Requires-Dist: ndx-franklab-novela
Requires-Dist: neuroconv
Requires-Dist: opencv-python
Requires-Dist: pynwb==3.0
Requires-Dist: scikit-learn
Requires-Dist: spikeinterface>=0.101.0
Requires-Dist: tables
Requires-Dist: tqdm
Provides-Extra: dev
Requires-Dist: black; extra == 'dev'
Requires-Dist: codespell; extra == 'dev'
Requires-Dist: pytest; extra == 'dev'
Requires-Dist: pytest-cov; extra == 'dev'
Requires-Dist: ruff; extra == 'dev'
Provides-Extra: test
Requires-Dist: pytest; extra == 'test'
Requires-Dist: pytest-cov; extra == 'test'
